lin/__init__.py
lin/apidoc.py
lin/config.py
lin/db.py
lin/encoder.py
lin/enums.py
lin/exception.py
lin/file.py
lin/form.py
lin/interface.py
lin/jwt.py
lin/lin.py
lin/loader.py
lin/logger.py
lin/manager.py
lin/model.py
lin/plugin.py
lin/redprint.py
lin/syslogger.py
lin/utils.py
Lin_CMS-0.4.11.dist-info/LICENSE
Lin_CMS-0.4.11.dist-info/METADATA
Lin_CMS-0.4.11.dist-info/WHEEL
Lin_CMS-0.4.11.dist-info/top_level.txt
Lin_CMS-0.4.11.dist-info/RECORD
