Metadata-Version: 2.1
Name: Lin-CMS
Version: 0.4.11
Summary: A simple and practical CMS implememted by flask
Home-page: https://pypi.org/project/Lin-CMS/
Author: pedroGao
Author-email: 1312342604@qq.com
Maintainer: sunlin92
Maintainer-email: sun.melodies@gmail.com
License: MIT
Keywords: flask,CMS,authority,jwt,openapi
Platform: any
Classifier: Development Status :: 3 - Alpha
Classifier: Environment :: Web Environment
Classifier: Intended Audience :: Developers
Classifier: License :: OSI Approved :: MIT License
Classifier: Operating System :: OS Independent
Classifier: Programming Language :: Python :: 3.8
License-File: LICENSE
Requires-Dist: Flask (==2.0.3)
Requires-Dist: Flask-JWT-Extended (==4.3.1)
Requires-Dist: Flask-SQLAlchemy (==2.5.1)
Requires-Dist: WTForms (==3.0.1)
Requires-Dist: tablib (==3.2.0)
Requires-Dist: spectree (==0.7.6)
Requires-Dist: SQLAlchemy (==1.4.46)
Requires-Dist: pydantic (==1.9.2)
